docufy_ocr/__init__.py
docufy_ocr/config.py
docufy_ocr/ocr.py
docufy_ocr/utils.py
docufy_ocr-0.1.7.dist-info/METADATA
docufy_ocr-0.1.7.dist-info/WHEEL
docufy_ocr-0.1.7.dist-info/licenses/LICENSE
docufy_ocr-0.1.7.dist-info/RECORD
