Metadata-Version: 2.4
Name: docufy_ocr
Version: 0.1.7
Summary: OCR library
Author: gabe cornejo
License-File: LICENSE
Requires-Python: >=3.12
Requires-Dist: pillow>=10.0.0
Requires-Dist: pymupdf>=1.26.3
Requires-Dist: pytesseract>=0.3.13
